[
    {
        "label": "Overview",
        "rows" : [
            [
                {"name": "name"},
                {"name": "parent"}
            ],
            [
                {"name": "status"},
                false
            ],
            [
                {"name": "dateStart"},
                {"name": "dateEnd"}
            ],
            [
                {"name": "duration"},
                false
            ],
            [
                {"name": "description"},
                false
            ]
        ]
    }
]